third_factor/__init__.py
third_factor/__main__.py
third_factor/third_factor.py
third_factor-0.0.4.dist-info/METADATA
third_factor-0.0.4.dist-info/WHEEL
third_factor-0.0.4.dist-info/entry_points.txt
third_factor-0.0.4.dist-info/top_level.txt
third_factor-0.0.4.dist-info/RECORD
