Metadata-Version: 2.1
Name: third-factor
Version: 0.0.4
Summary: Sometimes security is protection from yourself.
Home-page: https://github.com/dkolas/third-factor
Author: Steamship
Author-email: dave@steamship.com
